upd/__init__.py
upd/__main__.py
upd/__version__.py
upd/bed_utils.py
upd/cli.py
upd/utils.py
upd/vcf_tools.py
upd-0.2.dist-info/LICENSE
upd-0.2.dist-info/METADATA
upd-0.2.dist-info/WHEEL
upd-0.2.dist-info/entry_points.txt
upd-0.2.dist-info/top_level.txt
upd-0.2.dist-info/RECORD
