Metadata-Version: 2.1
Name: upd
Version: 0.2
Summary: Simple software to call UPD regions from germline exome/wgs trios.
Home-page: https://github.com/hrydbeck/upd
Author: Halfdan Rydbeck
Author-email: halfdan.rydbeck@regionostergotland.se
License: MIT
Keywords: vcf,variants,upd
Classifier: License :: OSI Approved :: MIT License
Classifier: Programming Language :: Python
Classifier: Programming Language :: Python :: 3
Classifier: Programming Language :: Python :: 3.6
Classifier: Operating System :: MacOS :: MacOS X
Classifier: Operating System :: Unix
Classifier: Intended Audience :: Science/Research
Classifier: Topic :: Scientific/Engineering :: Bio-Informatics
Requires-Python: >=3.6
License-File: LICENSE
Requires-Dist: click
Requires-Dist: coloredlogs
Provides-Extra: tests
Requires-Dist: pytest ; extra == 'tests'
Requires-Dist: pytest-cov ; extra == 'tests'
